pepperize_cdk_route53_health_check/__init__.py
pepperize_cdk_route53_health_check/py.typed
pepperize_cdk_route53_health_check/_jsii/__init__.py
pepperize_cdk_route53_health_check/_jsii/cdk-route53-health-check@0.0.754.jsii.tgz
pepperize_cdk_route53_health_check-0.0.754.dist-info/LICENSE
pepperize_cdk_route53_health_check-0.0.754.dist-info/METADATA
pepperize_cdk_route53_health_check-0.0.754.dist-info/WHEEL
pepperize_cdk_route53_health_check-0.0.754.dist-info/top_level.txt
pepperize_cdk_route53_health_check-0.0.754.dist-info/RECORD
